Workbook
Name ProductList: Products!$B$4:$B$11
Name PriceTable: Products!$B$4:$D$11
Name RegionTargets: Regions!$A$4:$C$7
Name SalesData: 'Sales 2025'!$A$2:$H$121
Name VatRate: 0.2

Sheet Summary
A1: Sales Report 2025
A2: Report date: | B2: =TODAY()
A4: Region | B4: Revenue | C4: Target | D4: Achieved | E4: Status | F4: Manager
A5: North | B5: =ROUND(SUMIF('Sales 2025'!$B$2:$B$121,A5,'Sales 2025'!$F$2:$F$121),2) | C5: =VLOOKUP(A5,Regions!$A$4:$C$7,3,FALSE) | D5: =IF(C5=0,0,B5/C5) | E5: =IF(D5>=1,"On target",IF(D5>=0.8,"Close","Behind")) | F5: =VLOOKUP(A5,Regions!$A$4:$B$7,2,FALSE)
A6: South | B6: =ROUND(SUMIF('Sales 2025'!$B$2:$B$121,A6,'Sales 2025'!$F$2:$F$121),2) | C6: =VLOOKUP(A6,Regions!$A$4:$C$7,3,FALSE) | D6: =IF(C6=0,0,B6/C6) | E6: =IF(D6>=1,"On target",IF(D6>=0.8,"Close","Behind")) | F6: =VLOOKUP(A6,Regions!$A$4:$B$7,2,FALSE)
A7: East | B7: =ROUND(SUMIF('Sales 2025'!$B$2:$B$121,A7,'Sales 2025'!$F$2:$F$121),2) | C7: =VLOOKUP(A7,Regions!$A$4:$C$7,3,FALSE) | D7: =IF(C7=0,0,B7/C7) | E7: =IF(D7>=1,"On target",IF(D7>=0.8,"Close","Behind")) | F7: =VLOOKUP(A7,Regions!$A$4:$B$7,2,FALSE)
A8: West | B8: =ROUND(SUMIF('Sales 2025'!$B$2:$B$121,A8,'Sales 2025'!$F$2:$F$121),2) | C8: =VLOOKUP(A8,Regions!$A$4:$C$7,3,FALSE) | D8: =IF(C8=0,0,B8/C8) | E8: =IF(D8>=1,"On target",IF(D8>=0.8,"Close","Behind")) | F8: =VLOOKUP(A8,Regions!$A$4:$B$7,2,FALSE)
A9: Total | B9: =SUM(B5:B8) | C9: =SUM(C5:C8) | D9: =IF(C9=0,0,B9/C9)
A11: Average order value | B11: =ROUND(AVERAGE('Sales 2025'!$F$2:$F$121),2)
A12: Orders with discount > 10% | B12: =COUNTIF('Sales 2025'!$G$2:$G$121,">0.1")
A13: Revenue incl. VAT | B13: =ROUND(B9*(1+VatRate),2)
A15: Month | B15: Revenue
A16: 45658 | B16: =SUMIF('Sales 2025'!$A$2:$A$121,">="&A16,'Sales 2025'!$F$2:$F$121)-SUMIF('Sales 2025'!$A$2:$A$121,">"&EOMONTH(A16,0),'Sales 2025'!$F$2:$F$121)
A17: 45689 | B17: =SUMIF('Sales 2025'!$A$2:$A$121,">="&A17,'Sales 2025'!$F$2:$F$121)-SUMIF('Sales 2025'!$A$2:$A$121,">"&EOMONTH(A17,0),'Sales 2025'!$F$2:$F$121)
A18: 45717 | B18: =SUMIF('Sales 2025'!$A$2:$A$121,">="&A18,'Sales 2025'!$F$2:$F$121)-SUMIF('Sales 2025'!$A$2:$A$121,">"&EOMONTH(A18,0),'Sales 2025'!$F$2:$F$121)
A19: 45748 | B19: =SUMIF('Sales 2025'!$A$2:$A$121,">="&A19,'Sales 2025'!$F$2:$F$121)-SUMIF('Sales 2025'!$A$2:$A$121,">"&EOMONTH(A19,0),'Sales 2025'!$F$2:$F$121)
A20: 45778 | B20: =SUMIF('Sales 2025'!$A$2:$A$121,">="&A20,'Sales 2025'!$F$2:$F$121)-SUMIF('Sales 2025'!$A$2:$A$121,">"&EOMONTH(A20,0),'Sales 2025'!$F$2:$F$121)
A21: 45809 | B21: =SUMIF('Sales 2025'!$A$2:$A$121,">="&A21,'Sales 2025'!$F$2:$F$121)-SUMIF('Sales 2025'!$A$2:$A$121,">"&EOMONTH(A21,0),'Sales 2025'!$F$2:$F$121)
A22: 45839 | B22: =SUMIF('Sales 2025'!$A$2:$A$121,">="&A22,'Sales 2025'!$F$2:$F$121)-SUMIF('Sales 2025'!$A$2:$A$121,">"&EOMONTH(A22,0),'Sales 2025'!$F$2:$F$121)
A23: 45870 | B23: =SUMIF('Sales 2025'!$A$2:$A$121,">="&A23,'Sales 2025'!$F$2:$F$121)-SUMIF('Sales 2025'!$A$2:$A$121,">"&EOMONTH(A23,0),'Sales 2025'!$F$2:$F$121)
A24: 45901 | B24: =SUMIF('Sales 2025'!$A$2:$A$121,">="&A24,'Sales 2025'!$F$2:$F$121)-SUMIF('Sales 2025'!$A$2:$A$121,">"&EOMONTH(A24,0),'Sales 2025'!$F$2:$F$121)
A25: 45931 | B25: =SUMIF('Sales 2025'!$A$2:$A$121,">="&A25,'Sales 2025'!$F$2:$F$121)-SUMIF('Sales 2025'!$A$2:$A$121,">"&EOMONTH(A25,0),'Sales 2025'!$F$2:$F$121)
A26: 45962 | B26: =SUMIF('Sales 2025'!$A$2:$A$121,">="&A26,'Sales 2025'!$F$2:$F$121)-SUMIF('Sales 2025'!$A$2:$A$121,">"&EOMONTH(A26,0),'Sales 2025'!$F$2:$F$121)
A27: 45992 | B27: =SUMIF('Sales 2025'!$A$2:$A$121,">="&A27,'Sales 2025'!$F$2:$F$121)-SUMIF('Sales 2025'!$A$2:$A$121,">"&EOMONTH(A27,0),'Sales 2025'!$F$2:$F$121)
A29: Sales dashboard (intranet)
A30: Go to the order list

Sheet Sales 2025
A1: Date | B1: Region | C1: Product | D1: Units | E1: Unit price | F1: Total | G1: Discount | H1: Rating
A2: 45660 | B2: West | C2: Standing Desk | D2: 1 | E2: 539 | F2: =D2*E2 | G2: 0 | H2: 2
A3: 45663 | B3: North | C3: Desk Organizer | D3: 4 | E3: 18.75 | F3: =D3*E3 | G3: 0 | H3: 5
A4: 45667 | B4: North | C4: Wireless Keyboard | D4: 13 | E4: 59.9 | F4: =D4*E4 | G4: 0 | H4: 2
A5: 45670 | B5: West | C5: Coffee Machine | D5: 6 | E5: 429 | F5: =D5*E5 | G5: 0 | H5: 5
A6: 45671 | B6: South | C6: Wireless Keyboard | D6: 8 | E6: 59.9 | F6: =D6*E6 | G6: 0.05 | H6: 5
A7: 45674 | B7: North | C7: 27-inch Monitor | D7: 9 | E7: 319 | F7: =D7*E7 | G7: 0.1 | H7: 1
A8: 45679 | B8: West | C8: Noise-cancelling Headset | D8: 8 | E8: 149 | F8: =D8*E8 | G8: 0.05 | H8: 3
A9: 45682 | B9: West | C9: Coffee Machine | D9: 7 | E9: 429 | F9: =D9*E9 | G9: 0 | H9: 5
A10: 45684 | B10: North | C10: A4 Paper (box of 5 reams) | D10: 40 | E10: 27.5 | F10: =D10*E10 | G10: 0.05 | H10: 3
A11: 45686 | B11: East | C11: 27-inch Monitor | D11: 14 | E11: 319 | F11: =D11*E11 | G11: 0.08 | H11: 3
A12: 45690 | B12: East | C12: Standing Desk | D12: 9 | E12: 539 | F12: =D12*E12 | G12: 0.05 | H12: 3
A13: 45694 | B13: East | C13: 27-inch Monitor | D13: 1 | E13: 319 | F13: =D13*E13 | G13: 0.1 | H13: 5
... A121: 46017 | B121: South | C121: Ergonomic Office Chair | D121: 4 | E121: 249 | F121: =D121*E121 | G121: 0.15 | H121: 4

Sheet Products
A1: Product catalogue
A3: Code | B3: Product | C3: Category | D3: Unit price | E3: In stock | G3: Supplier portal
A4: P-100 | B4: Ergonomic Office Chair | C4: Furniture | D4: 249 | E4: TRUE
A5: P-110 | B5: Standing Desk | C5: Furniture | D5: 539 | E5: FALSE
A6: P-200 | B6: 27-inch Monitor | C6: Electronics | D6: 319 | E6: TRUE
A7: P-210 | B7: Wireless Keyboard | C7: Electronics | D7: 59.9 | E7: TRUE
A8: P-220 | B8: Noise-cancelling Headset | C8: Electronics | D8: 149 | E8: TRUE
A9: P-300 | B9: A4 Paper (box of 5 reams) | C9: Supplies | D9: 27.5 | E9: FALSE
A10: P-310 | B10: Desk Organizer | C10: Supplies | D10: 18.75 | E10: TRUE
A11: P-400 | B11: Coffee Machine | C11: Appliances | D11: 429 | E11: TRUE

Sheet Regions
A1: Regional targets 2025
A3: Region | B3: Manager | C3: Annual target | D3: Share of target
A4: North | B4: Emily Carter | C4: 60000 | D4: =C4/SUM($C$4:$C$7)
A5: South | B5: Daniel Moore | C5: 50000 | D5: =C5/SUM($C$4:$C$7)
A6: East | B6: Olivia Bennett | C6: 55000 | D6: =C6/SUM($C$4:$C$7)
A7: West | B7: Lucas Harris | C7: 65000 | D7: =C7/SUM($C$4:$C$7)
A8: Total | C8: =SUM(C4:C7)
